src/controller.v
`timescale 1ns/1ps
module controller (
    input clk, rst,
    input [2:0] opcode,
    input zero,
    output reg sel, rd, ld_ir, halt, inc_pc, ld_ac, ld_pc, wr, data_e
);
    parameter INST_ADDR  = 3'd0,
              INST_FETCH = 3'd1,
              INST_LOAD  = 3'd2,
              IDLE       = 3'd3,
              OP_ADDR    = 3'd4,
              OP_FETCH   = 3'd5,
              ALU_OP     = 3'd6,
              STORE      = 3'd7;
    
    reg [2:0] state, next_state;
    reg skip_next;

    always @(posedge clk or posedge rst) begin
        if (rst) begin
            state <= INST_ADDR;
            skip_next <= 1'b0;
        end
        else if (!halt) begin
            state <= next_state;
            if (state == ALU_OP && opcode == 3'b001 && zero)
                skip_next <= 1'b1;
            else if (state == STORE)
                skip_next <= 1'b0;
        end
    end

    always @(*) begin
        case (state)
            INST_ADDR:  next_state = INST_FETCH;
            INST_FETCH: next_state = INST_LOAD;
            INST_LOAD:  next_state = IDLE;
            IDLE:       next_state = OP_ADDR;
            OP_ADDR:    next_state = OP_FETCH;
            OP_FETCH:   next_state = ALU_OP;
            ALU_OP:     next_state = STORE;
            STORE:      next_state = INST_ADDR;
            default:    next_state = INST_ADDR;
        endcase
    end

    always @(*) begin
        sel = 1'b0;
        rd = 1'b0;
        ld_ir = 1'b0;
        halt = 1'b0;
        inc_pc = 1'b0;
        ld_ac = 1'b0;
        ld_pc = 1'b0;
        wr = 1'b0;
        data_e = 1'b0;
        
        case (state)
            INST_ADDR: sel = 1'b1;
            INST_FETCH: begin
                sel = 1'b1;
                rd = 1'b1;
            end
            INST_LOAD: begin
                sel = 1'b1;
                rd = 1'b1;
                ld_ir = 1'b1;
            end
            IDLE: sel = 1'b1;
            OP_ADDR: begin
                if (opcode == 3'b010 || opcode == 3'b011 || opcode == 3'b100 || opcode == 3'b101 || opcode == 3'b110)
                    sel = 1'b0;
            end
            OP_FETCH: begin
                if (opcode == 3'b010 || opcode == 3'b011 || opcode == 3'b100 || opcode == 3'b101 || opcode == 3'b110)
                    rd = 1'b1;
            end
            ALU_OP: begin
                if (opcode == 3'b010 || opcode == 3'b011 || opcode == 3'b100 || opcode == 3'b101)
                    ld_ac = 1'b1;
                if (opcode == 3'b001 && zero)
                    inc_pc = 1'b1;
            end
            STORE: begin
                case (opcode)
                    3'b110: begin
                        wr = 1'b1;
                        data_e = 1'b1;
			inc_pc = 1'b1;
                    end
                    3'b000: halt = 1'b1;
                    3'b111: ld_pc = 1'b1;
                    default: begin
                        inc_pc = 1'b1;
                        if (skip_next && opcode == 3'b001)
                            inc_pc = 1'b1;
                    end
                endcase
            end
        endcase
    end

    always @(posedge clk) begin
        $display("Controller: state = %d, opcode = %b, zero = %b, sel = %b, rd = %b, ld_ir = %b, halt = %b, inc_pc = %b, ld_ac = %b, ld_pc = %b, wr = %b, data_e = %b, skip_next = %b",
                 state, opcode, zero, sel, rd, ld_ir, halt, inc_pc, ld_ac, ld_pc, wr, data_e, skip_next);
        if (state == ALU_OP && opcode == 3'b001)
            $display("SKZ: zero = %b, skip_next = %b, inc_pc = %b", zero, skip_next, inc_pc);
        if (state == STORE && skip_next)
            $display("SKZ STORE: skip_next = %b, inc_pc = %b", skip_next, inc_pc);
    end
endmodule

src/register.v
`timescale 1ns/1ps
module register (
    input clk, rst, load,
    input [7:0] in,
    output reg [7:0] out
);
    always @(posedge clk or posedge rst) begin
        if (rst) out <= 8'b0;
        else if (load) out <= in;
    end
endmodule

src/alu.v
`timescale 1ns/1ps
module alu (
    input [2:0] opcode,
    input [7:0] inA, inB,
    output reg [7:0] out,
    output reg is_zero
);
    always @(*) begin
        case (opcode)
            3'b000: out = 8'b0;            // HLT
            3'b001: out = inA;             // SKZ 
            3'b010: out = inA + inB;       // ADD
            3'b011: out = inA & inB;       // AND
            3'b100: out = inA ^ inB;       // XOR
            3'b101: out = inB;             // LDA
            3'b110: out = inA;             // STO
            3'b111: out = 8'b0;            // JMP
            default: out = 8'b0;          
        endcase
        is_zero = (out == 8'b0) ? 1'b1 : 1'b0; 
    end

    // Debug
    always @(*) begin
        $display("ALU: opcode = %b, inA = %h, inB = %h, out = %h, is_zero = %b", opcode, inA, inB, out, is_zero);
    end
endmodule

src/memory.v
`timescale 1ns/1ps
module memory (
    input clk, rd, wr,
    input [4:0] addr,
    inout [7:0] data
);
    reg [7:0] mem[31:0];
    reg [7:0] data_out;

    initial $readmemb("../test/program2.mem", mem); // Tên tệp tạm thời, sẽ được ghi đè

    always @(posedge clk) begin
        if (wr && !rd) mem[addr] <= data;
    end

    always @(*) begin
        if (rd && !wr) data_out = mem[addr];
        else data_out = 8'bz;
    end

    assign data = (rd && !wr) ? data_out : 8'bz;

    // Debug
    always @(posedge clk) begin
        if (rd && !wr)
            $display("Memory read: addr = %h, data = %h", addr, data_out);
        if (wr && !rd)
            $display("Memory write: addr = %h, data = %h", addr, data);
    end
endmodule

src/address_mux.v
`timescale 1ns/1ps
module address_mux #(
    parameter WIDTH = 5
) (
    input sel,
    input [WIDTH-1:0] pc_addr, op_addr,
    output [WIDTH-1:0] addr_out
);
    assign addr_out = sel ? pc_addr : op_addr;
endmodule

src/program_counter.v
`timescale 1ns/1ps
module program_counter (
    input clk, rst, ld_pc, inc_pc,
    input [4:0] load_val,
    output reg [4:0] pc
);
    always @(posedge clk or posedge rst) begin
        if (rst) pc <= 5'b0;
        else if (ld_pc) pc <= load_val;
        else if (inc_pc) pc <= pc + 1;
    end
endmodule

src/risc_cpu.v
`timescale 1ns/1ps
module risc_cpu (
    input clk, rst
);
    wire [4:0] pc_out;
    wire [4:0] addr_mux_out;
    wire [7:0] mem_data;
    wire [7:0] ir_out;
    wire [7:0] ac_out;
    wire [7:0] alu_out;
    wire is_zero;
    wire [2:0] opcode;
    wire [4:0] operand;
    wire sel, rd, ld_ir, halt, inc_pc, ld_ac, ld_pc, wr, data_e;

    reg [7:0] mem_data_reg;
    always @(posedge clk) begin
        if (rst) mem_data_reg <= 8'b0;
        else if (ctrl.state == 5 && ctrl.rd) 
            mem_data_reg <= mem_data;
    end

    reg [2:0] opcode_reg;
    always @(posedge clk) begin
        if (rst) opcode_reg <= 3'b0;
        else opcode_reg <= ir_out[7:5];
    end

    // Kết nối các mô-đun
    program_counter pc (.clk(clk), .rst(rst), .ld_pc(ld_pc), .inc_pc(inc_pc), .load_val(operand), .pc(pc_out));
    address_mux addr_mux (.sel(sel), .pc_addr(pc_out), .op_addr(operand), .addr_out(addr_mux_out));
    memory mem (.clk(clk), .rd(rd), .wr(wr), .addr(addr_mux_out), .data(mem_data));
    register ir (.clk(clk), .rst(rst), .load(ld_ir), .in(mem_data), .out(ir_out));
    
    alu alu_inst (.opcode(opcode), .inA(ac_out), .inB(mem_data_reg), .out(alu_out), .is_zero(is_zero));
    register ac (.clk(clk), .rst(rst), .load(ld_ac), .in(alu_out), .out(ac_out));
    
    controller ctrl (.clk(clk), .rst(rst), .opcode(opcode), .zero(is_zero),
                     .sel(sel), .rd(rd), .ld_ir(ld_ir), .halt(halt), .inc_pc(inc_pc),
                     .ld_ac(ld_ac), .ld_pc(ld_pc), .wr(wr), .data_e(data_e));

    assign opcode = opcode_reg;
    assign operand = ir_out[4:0];
    
    assign mem_data = (data_e && wr && !rd) ? ac_out : 8'bz;

    always @(posedge clk) begin
        $display("CPU: PC = %h, AC = %h, IR = %h, opcode = %b, alu_out = %h, ld_ac = %b, is_zero = %b, mem_data = %h, mem_data_reg = %h",
                 pc_out, ac_out, ir_out, opcode, alu_out, ld_ac, is_zero, mem_data, mem_data_reg);
    end
endmodule

test/tb_risc_cpu.v
`timescale 1ns/1ps
module tb_risc_cpu;
    reg clk, rst;
    risc_cpu uut (.clk(clk), .rst(rst));

    initial begin
        clk = 0;
        forever #5 clk = ~clk; 
    end

    initial begin
        $recordfile("waves");
        $recordvars("depth=0", tb_risc_cpu);
    end

    initial begin
        $dumpfile("../sim/risc_cpu.vcd");
        $dumpvars(0, tb_risc_cpu);

        $display("Testing Program 3 (LDA, AND, XOR, ADD, SKZ, STO, JMP)...");
        rst = 1;
        #20 rst = 0;
        #5000;
        if (uut.halt && uut.pc_out == 5'h10)
            $display("Program 3 PASSED: Halted at %h", uut.pc_out);
        else
            $display("Program 3 FAILED: PC = %h, Halt = %b", uut.pc_out, uut.halt);
        $finish;
    end
endmodule

sim/risc_cpu.vcd
$date
    Apr 12, 2025  18:14:54
$end
$version
    TOOL:	xmsim(64)	24.03-s011
$end
$timescale
    1 ps
$end

$scope module tb_risc_cpu $end
$var reg       1 !    clk $end
$var reg       1 "    rst $end

$scope module uut $end
$var wire      1 #    clk  $end
$var wire      1 $    rst  $end
$var wire      5 %    pc_out [4:0] $end
$var wire      5 &    addr_mux_out [4:0] $end
$var wire      8 '    mem_data [7:0] $end
$var wire      8 (    ir_out [7:0] $end
$var wire      8 )    ac_out [7:0] $end
$var wire      8 *    alu_out [7:0] $end
$var wire      1 +    is_zero  $end
$var wire      3 ,    opcode [2:0] $end
$var wire      5 -    operand [4:0] $end
$var wire      1 .    sel  $end
$var wire      1 /    rd  $end
$var wire      1 0    ld_ir  $end
$var wire      1 1    halt  $end
$var wire      1 2    inc_pc  $end
$var wire      1 3    ld_ac  $end
$var wire      1 4    ld_pc  $end
$var wire      1 5    wr  $end
$var wire      1 6    data_e  $end
$var reg       8 7    mem_data_reg [7:0] $end
$var reg       3 8    opcode_reg [2:0] $end

$scope module pc $end
$var wire      1 #    clk  $end
$var wire      1 $    rst  $end
$var wire      1 4    ld_pc  $end
$var wire      1 2    inc_pc  $end
$var wire      5 -    load_val [4:0] $end
$var reg       5 9    pc [4:0] $end
$upscope $end


$scope module addr_mux $end
$var parameter 32 :    WIDTH $end
$var wire      1 .    sel  $end
$var wire      5 %    pc_addr [4:0] $end
$var wire      5 -    op_addr [4:0] $end
$var wire      5 &    addr_out [4:0] $end
$upscope $end


$scope module mem $end
$var wire      1 #    clk  $end
$var wire      1 /    rd  $end
$var wire      1 5    wr  $end
$var wire      5 &    addr [4:0] $end
$var wire      8 '    data [7:0] $end
$var reg       8 ;    mem[31] [7:0] $end
$var reg       8 <    mem[30] [7:0] $end
$var reg       8 =    mem[29] [7:0] $end
$var reg       8 >    mem[28] [7:0] $end
$var reg       8 ?    mem[27] [7:0] $end
$var reg       8 @    mem[26] [7:0] $end
$var reg       8 A    mem[25] [7:0] $end
$var reg       8 B    mem[24] [7:0] $end
$var reg       8 C    mem[23] [7:0] $end
$var reg       8 D    mem[22] [7:0] $end
$var reg       8 E    mem[21] [7:0] $end
$var reg       8 F    mem[20] [7:0] $end
$var reg       8 G    mem[19] [7:0] $end
$var reg       8 H    mem[18] [7:0] $end
$var reg       8 I    mem[17] [7:0] $end
$var reg       8 J    mem[16] [7:0] $end
$var reg       8 K    mem[15] [7:0] $end
$var reg       8 L    mem[14] [7:0] $end
$var reg       8 M    mem[13] [7:0] $end
$var reg       8 N    mem[12] [7:0] $end
$var reg       8 O    mem[11] [7:0] $end
$var reg       8 P    mem[10] [7:0] $end
$var reg       8 Q    mem[9] [7:0] $end
$var reg       8 R    mem[8] [7:0] $end
$var reg       8 S    mem[7] [7:0] $end
$var reg       8 T    mem[6] [7:0] $end
$var reg       8 U    mem[5] [7:0] $end
$var reg       8 V    mem[4] [7:0] $end
$var reg       8 W    mem[3] [7:0] $end
$var reg       8 X    mem[2] [7:0] $end
$var reg       8 Y    mem[1] [7:0] $end
$var reg       8 Z    mem[0] [7:0] $end
$var reg       8 [    data_out [7:0] $end
$upscope $end


$scope module ir $end
$var wire      1 #    clk  $end
$var wire      1 $    rst  $end
$var wire      1 0    load  $end
$var wire      8 '    in [7:0] $end
$var reg       8 \    out [7:0] $end
$upscope $end


$scope module alu_inst $end
$var wire      3 ,    opcode [2:0] $end
$var wire      8 )    inA [7:0] $end
$var wire      8 ]    inB [7:0] $end
$var reg       8 ^    out [7:0] $end
$var reg       1 _    is_zero $end
$upscope $end


$scope module ac $end
$var wire      1 #    clk  $end
$var wire      1 $    rst  $end
$var wire      1 3    load  $end
$var wire      8 *    in [7:0] $end
$var reg       8 `    out [7:0] $end
$upscope $end


$scope module ctrl $end
$var wire      1 #    clk  $end
$var wire      1 $    rst  $end
$var wire      3 ,    opcode [2:0] $end
$var wire      1 +    zero  $end
$var reg       1 a    sel $end
$var reg       1 b    rd $end
$var reg       1 c    ld_ir $end
$var reg       1 d    halt $end
$var reg       1 e    inc_pc $end
$var reg       1 f    ld_ac $end
$var reg       1 g    ld_pc $end
$var reg       1 h    wr $end
$var reg       1 i    data_e $end
$var parameter  3 j    INST_ADDR $end
$var parameter  3 k    INST_FETCH $end
$var parameter  3 l    INST_LOAD $end
$var parameter  3 m    IDLE $end
$var parameter  3 n    OP_ADDR $end
$var parameter  3 o    OP_FETCH $end
$var parameter  3 p    ALU_OP $end
$var parameter  3 q    STORE $end
$var reg       3 r    state [2:0] $end
$var reg       3 s    next_state [2:0] $end
$var reg       1 t    skip_next $end
$upscope $end

$upscope $end

$upscope $end

$enddefinitions $end
$dumpvars
b111 q
b110 p
b101 o
b100 n
b11 m
b10 l
b1 k
b0 j
b101 :
0!
1"
0#
1$
b0 %
b0 &
bz '
b0 (
b0 )
b0 *
1+
bx ,
b0 -
1.
0/
00
01
02
03
04
05
06
bx 7
bx 8
b0 9
bx ;
bx <
b0 =
b11111111 >
b10101010 ?
b1 @
b0 A
b0 B
b0 C
b0 D
b0 E
b0 F
b0 G
b0 H
b11100000 I
b0 J
b0 K
b100000 L
b1011101 M
b10111010 N
b11011101 O
b1011010 P
b10011100 Q
b0 R
b11101001 S
b100000 T
b1011010 U
b0 V
b100000 W
b10011011 X
b1111100 Y
b10111011 Z
bz [
b0 \
bx ]
b0 ^
1_
b0 `
1a
0b
0c
0d
0e
0f
0g
0h
0i
b0 r
b1 s
0t
$end
#5000
1!
1#
b0 8
b0 7
b0 ]
b0 ,
0a
1a
#10000
0!
0#
#15000
1!
1#
#20000
0"
0!
0#
0$
#25000
1!
1#
b1 r
b10 s
0a
1a
1b
1/
b10111011 [
b10111011 '
#30000
0!
0#
#35000
1!
1#
b10 r
b11 s
0a
0b
1a
1b
1c
10
#40000
0!
0#
#45000
1!
1#
b11 r
b10111011 \
b100 s
0a
0b
0c
1a
00
0/
b10111011 (
bz [
b11011 -
bz '
#50000
0!
0#
#55000
1!
1#
b100 r
b101 8
b101 s
0a
0.
b101 ,
b11011 &
#60000
0!
0#
#65000
1!
1#
b101 r
b110 s
1b
1/
b10101010 [
b10101010 '
#70000
0!
0#
#75000
1!
1#
b110 r
b10101010 7
b111 s
0b
1f
b10101010 ]
13
0/
b10101010 ^
0_
bz [
0+
b10101010 *
bz '
0f
1f
#80000
0!
0#
#85000
1!
1#
b111 r
b10101010 `
b0 s
0f
1e
12
03
b10101010 )
#90000
0!
0#
#95000
1!
1#
b0 r
b1 9
b1 s
0e
1a
1.
02
b1 %
b1 &
#100000
0!
0#
#105000
1!
1#
b1 r
b10 s
0a
1a
1b
1/
b1111100 [
b1111100 '
#110000
0!
0#
#115000
1!
1#
b10 r
b11 s
0a
0b
1a
1b
1c
10
#120000
0!
0#
#125000
1!
1#
b11 r
b1111100 \
b100 s
0a
0b
0c
1a
00
0/
b1111100 (
bz [
b11100 -
bz '
#130000
0!
0#
#135000
1!
1#
b100 r
b11 8
b101 s
0a
0.
b11 ,
b11100 &
#140000
0!
0#
#145000
1!
1#
b101 r
b110 s
1b
1/
b11111111 [
b11111111 '
#150000
0!
0#
#155000
1!
1#
b110 r
b11111111 7
b111 s
0b
1f
b11111111 ]
13
0/
bz [
bz '
#160000
0!
0#
#165000
1!
1#
b111 r
b0 s
0f
1e
12
03
#170000
0!
0#
#175000
1!
1#
b0 r
b10 9
b1 s
0e
1a
1.
02
b10 %
b10 &
#180000
0!
0#
#185000
1!
1#
b1 r
b10 s
0a
1a
1b
1/
b10011011 [
b10011011 '
#190000
0!
0#
#195000
1!
1#
b10 r
b11 s
0a
0b
1a
1b
1c
10
#200000
0!
0#
#205000
1!
1#
b11 r
b10011011 \
b100 s
0a
0b
0c
1a
00
0/
b10011011 (
bz [
b11011 -
bz '
#210000
0!
0#
#215000
1!
1#
b100 r
b100 8
b101 s
0a
0.
b100 ,
b1010101 ^
b1010101 *
b11011 &
#220000
0!
0#
#225000
1!
1#
b101 r
b110 s
1b
1/
b10101010 [
b10101010 '
#230000
0!
0#
#235000
1!
1#
b110 r
b10101010 7
b111 s
0b
1f
b10101010 ]
13
0/
b0 ^
1_
bz [
1+
b0 *
bz '
0f
1f
#240000
0!
0#
#245000
1!
1#
b111 r
b0 `
b0 s
0f
1e
12
03
b0 )
b10101010 ^
0_
0+
b10101010 *
0e
1e
#250000
0!
0#
#255000
1!
1#
b0 r
b11 9
b1 s
0e
1a
1.
02
b11 %
b11 &
#260000
0!
0#
#265000
1!
1#
b1 r
b10 s
0a
1a
1b
1/
b100000 [
b100000 '
#270000
0!
0#
#275000
1!
1#
b10 r
b11 s
0a
0b
1a
1b
1c
10
#280000
0!
0#
#285000
1!
1#
b11 r
b100000 \
b100 s
0a
0b
0c
1a
00
0/
b100000 (
bz [
b0 -
bz '
#290000
0!
0#
#295000
1!
1#
b100 r
b1 8
b101 s
0a
0.
b1 ,
b0 ^
1_
1+
b0 *
b0 &
#300000
0!
0#
#305000
1!
1#
b101 r
b110 s
#310000
0!
0#
#315000
1!
1#
b110 r
b111 s
1e
12
#320000
0!
0#
#325000
1!
1#
b111 r
1t
b100 9
b0 s
0e
1e
b100 %
#330000
0!
0#
#335000
1!
1#
b0 r
0t
b101 9
b1 s
0e
1a
1.
02
b101 %
b101 &
#340000
0!
0#
#345000
1!
1#
b1 r
b10 s
0a
1a
1b
1/
b1011010 [
b1011010 '
#350000
0!
0#
#355000
1!
1#
b10 r
b11 s
0a
0b
1a
1b
1c
10
#360000
0!
0#
#365000
1!
1#
b11 r
b1011010 \
b100 s
0a
0b
0c
1a
00
0/
b1011010 (
bz [
b11010 -
bz '
#370000
0!
0#
#375000
1!
1#
b100 r
b10 8
b101 s
0a
0.
b10 ,
b10101010 ^
0_
0+
b10101010 *
b11010 &
#380000
0!
0#
#385000
1!
1#
b101 r
b110 s
1b
1/
b1 [
b1 '
#390000
0!
0#
#395000
1!
1#
b110 r
b1 7
b111 s
0b
1f
b1 ]
13
0/
b1 ^
bz [
b1 *
bz '
#400000
0!
0#
#405000
1!
1#
b111 r
b1 `
b0 s
0f
1e
12
03
b1 )
b10 ^
b10 *
#410000
0!
0#
#415000
1!
1#
b0 r
b110 9
b1 s
0e
1a
1.
02
b110 %
b110 &
#420000
0!
0#
#425000
1!
1#
b1 r
b10 s
0a
1a
1b
1/
b100000 [
b100000 '
#430000
0!
0#
#435000
1!
1#
b10 r
b11 s
0a
0b
1a
1b
1c
10
#440000
0!
0#
#445000
1!
1#
b11 r
b100000 \
b100 s
0a
0b
0c
1a
00
0/
b100000 (
bz [
b0 -
bz '
#450000
0!
0#
#455000
1!
1#
b100 r
b1 8
b101 s
0a
0.
b1 ,
b1 ^
b1 *
b0 &
#460000
0!
0#
#465000
1!
1#
b101 r
b110 s
#470000
0!
0#
#475000
1!
1#
b110 r
b111 s
#480000
0!
0#
#485000
1!
1#
b111 r
b0 s
1e
12
#490000
0!
0#
#495000
1!
1#
b0 r
b111 9
b1 s
0e
1a
1.
02
b111 %
b111 &
#500000
0!
0#
#505000
1!
1#
b1 r
b10 s
0a
1a
1b
1/
b11101001 [
b11101001 '
#510000
0!
0#
#515000
1!
1#
b10 r
b11 s
0a
0b
1a
1b
1c
10
#520000
0!
0#
#525000
1!
1#
b11 r
b11101001 \
b100 s
0a
0b
0c
1a
00
0/
b11101001 (
bz [
b1001 -
bz '
#530000
0!
0#
#535000
1!
1#
b100 r
b111 8
b101 s
0a
0.
b111 ,
b0 ^
1_
1+
b0 *
b1001 &
#540000
0!
0#
#545000
1!
1#
b101 r
b110 s
#550000
0!
0#
#555000
1!
1#
b110 r
b111 s
#560000
0!
0#
#565000
1!
1#
b111 r
b0 s
1g
14
#570000
0!
0#
#575000
1!
1#
b0 r
b1001 9
b1 s
0g
1a
1.
04
b1001 %
#580000
0!
0#
#585000
1!
1#
b1 r
b10 s
0a
1a
1b
1/
b10011100 [
b10011100 '
#590000
0!
0#
#595000
1!
1#
b10 r
b11 s
0a
0b
1a
1b
1c
10
#600000
0!
0#
#605000
1!
1#
b11 r
b10011100 \
b100 s
0a
0b
0c
1a
00
0/
b10011100 (
bz [
b11100 -
bz '
#610000
0!
0#
#615000
1!
1#
b100 r
b100 8
b101 s
0a
0.
b100 ,
b11100 &
#620000
0!
0#
#625000
1!
1#
b101 r
b110 s
1b
1/
b11111111 [
b11111111 '
#630000
0!
0#
#635000
1!
1#
b110 r
b11111111 7
b111 s
0b
1f
b11111111 ]
13
0/
b11111110 ^
0_
bz [
0+
b11111110 *
bz '
0f
1f
#640000
0!
0#
#645000
1!
1#
b111 r
b11111110 `
b0 s
0f
1e
12
03
b11111110 )
b1 ^
b1 *
#650000
0!
0#
#655000
1!
1#
b0 r
b1010 9
b1 s
0e
1a
1.
02
b1010 %
b1010 &
#660000
0!
0#
#665000
1!
1#
b1 r
b10 s
0a
1a
1b
1/
b1011010 [
b1011010 '
#670000
0!
0#
#675000
1!
1#
b10 r
b11 s
0a
0b
1a
1b
1c
10
#680000
0!
0#
#685000
1!
1#
b11 r
b1011010 \
b100 s
0a
0b
0c
1a
00
0/
b1011010 (
bz [
b11010 -
bz '
#690000
0!
0#
#695000
1!
1#
b100 r
b10 8
b101 s
0a
0.
b10 ,
b11111101 ^
b11111101 *
b11010 &
#700000
0!
0#
#705000
1!
1#
b101 r
b110 s
1b
1/
b1 [
b1 '
#710000
0!
0#
#715000
1!
1#
b110 r
b1 7
b111 s
0b
1f
b1 ]
13
0/
b11111111 ^
bz [
b11111111 *
bz '
#720000
0!
0#
#725000
1!
1#
b111 r
b11111111 `
b0 s
0f
1e
12
03
b11111111 )
b0 ^
1_
1+
b0 *
0e
1e
#730000
0!
0#
#735000
1!
1#
b0 r
b1011 9
b1 s
0e
1a
1.
02
b1011 %
b1011 &
#740000
0!
0#
#745000
1!
1#
b1 r
b10 s
0a
1a
1b
1/
b11011101 [
b11011101 '
#750000
0!
0#
#755000
1!
1#
b10 r
b11 s
0a
0b
1a
1b
1c
10
#760000
0!
0#
#765000
1!
1#
b11 r
b11011101 \
b100 s
0a
0b
0c
1a
00
0/
b11011101 (
bz [
b11101 -
bz '
#770000
0!
0#
#775000
1!
1#
b100 r
b110 8
b101 s
0a
0.
b110 ,
b11111111 ^
0_
0+
b11111111 *
b11101 &
#780000
0!
0#
#785000
1!
1#
b101 r
b110 s
1b
1/
b0 [
b0 '
#790000
0!
0#
#795000
1!
1#
b110 r
b0 7
b111 s
0b
b0 ]
0/
bz [
bz '
#800000
0!
0#
#805000
1!
1#
b111 r
b0 s
1h
1i
1e
12
16
15
b11111111 '
#810000
0!
0#
#815000
1!
1#
b0 r
b1100 9
b11111111 =
b1 s
0e
0h
0i
1a
1.
06
05
02
b1100 %
b1100 &
bz '
#820000
0!
0#
#825000
1!
1#
b1 r
b10 s
0a
1a
1b
1/
b10111010 [
b10111010 '
#830000
0!
0#
#835000
1!
1#
b10 r
b11 s
0a
0b
1a
1b
1c
10
#840000
0!
0#
#845000
1!
1#
b11 r
b10111010 \
b100 s
0a
0b
0c
1a
00
0/
b10111010 (
bz [
b11010 -
bz '
#850000
0!
0#
#855000
1!
1#
b100 r
b101 8
b101 s
0a
0.
b101 ,
b0 ^
1_
1+
b0 *
b11010 &
#860000
0!
0#
#865000
1!
1#
b101 r
b110 s
1b
1/
b1 [
b1 '
#870000
0!
0#
#875000
1!
1#
b110 r
b1 7
b111 s
0b
1f
b1 ]
13
0/
b1 ^
0_
bz [
0+
b1 *
bz '
0f
1f
#880000
0!
0#
#885000
1!
1#
b111 r
b1 `
b0 s
0f
1e
12
03
b1 )
#890000
0!
0#
#895000
1!
1#
b0 r
b1101 9
b1 s
0e
1a
1.
02
b1101 %
b1101 &
#900000
0!
0#
#905000
1!
1#
b1 r
b10 s
0a
1a
1b
1/
b1011101 [
b1011101 '
#910000
0!
0#
#915000
1!
1#
b10 r
b11 s
0a
0b
1a
1b
1c
10
#920000
0!
0#
#925000
1!
1#
b11 r
b1011101 \
b100 s
0a
0b
0c
1a
00
0/
b1011101 (
bz [
b11101 -
bz '
#930000
0!
0#
#935000
1!
1#
b100 r
b10 8
b101 s
0a
0.
b10 ,
b10 ^
b10 *
b11101 &
#940000
0!
0#
#945000
1!
1#
b101 r
b110 s
1b
1/
b11111111 [
b11111111 '
#950000
0!
0#
#955000
1!
1#
b110 r
b11111111 7
b111 s
0b
1f
b11111111 ]
13
0/
b0 ^
1_
bz [
1+
b0 *
bz '
0f
1f
#960000
0!
0#
#965000
1!
1#
b111 r
b0 `
b0 s
0f
1e
12
03
b0 )
b11111111 ^
0_
0+
b11111111 *
0e
1e
#970000
0!
0#
#975000
1!
1#
b0 r
b1110 9
b1 s
0e
1a
1.
02
b1110 %
b1110 &
#980000
0!
0#
#985000
1!
1#
b1 r
b10 s
0a
1a
1b
1/
b100000 [
b100000 '
#990000
0!
0#
#995000
1!
1#
b10 r
b11 s
0a
0b
1a
1b
1c
10
#1000000
0!
0#
#1005000
1!
1#
b11 r
b100000 \
b100 s
0a
0b
0c
1a
00
0/
b100000 (
bz [
b0 -
bz '
#1010000
0!
0#
#1015000
1!
1#
b100 r
b1 8
b101 s
0a
0.
b1 ,
b0 ^
1_
1+
b0 *
b0 &
#1020000
0!
0#
#1025000
1!
1#
b101 r
b110 s
#1030000
0!
0#
#1035000
1!
1#
b110 r
b111 s
1e
12
#1040000
0!
0#
#1045000
1!
1#
b111 r
1t
b1111 9
b0 s
0e
1e
b1111 %
#1050000
0!
0#
#1055000
1!
1#
b0 r
0t
b10000 9
b1 s
0e
1a
1.
02
b10000 %
b10000 &
#1060000
0!
0#
#1065000
1!
1#
b1 r
b10 s
0a
1a
1b
1/
b0 [
b0 '
#1070000
0!
0#
#1075000
1!
1#
b10 r
b11 s
0a
0b
1a
1b
1c
10
#1080000
0!
0#
#1085000
1!
1#
b11 r
b0 \
b100 s
0a
0b
0c
1a
00
0/
b0 (
bz [
bz '
#1090000
0!
0#
#1095000
1!
1#
b100 r
b0 8
b101 s
0a
0.
b0 ,
b0 &
#1100000
0!
0#
#1105000
1!
1#
b101 r
b110 s
#1110000
0!
0#
#1115000
1!
1#
b110 r
b111 s
#1120000
0!
0#
#1125000
1!
1#
b111 r
b0 s
1d
11
